fastmrz/__init__.py
fastmrz/cli.py
fastmrz/fastmrz.py
fastmrz/main.py
fastmrz/model/mrz_seg.onnx
fastmrz/model/mrz_seg.tflite
fastmrz-2.1.1.dist-info/LICENSE
fastmrz-2.1.1.dist-info/METADATA
fastmrz-2.1.1.dist-info/WHEEL
fastmrz-2.1.1.dist-info/top_level.txt
fastmrz-2.1.1.dist-info/RECORD
