Metadata-Version: 2.1
Name: fastmrz
Version: 2.1.1
Summary: Extracts the Machine Readable Zone (MRZ) data from document images
Home-page: https://github.com/sivakumar-mahalingam/fastmrz/
Author: Sivakumar Mahalingam
License: AGPLv3
Project-URL: Source, https://github.com/sivakumar-mahalingam/fastmrz
Project-URL: Tracker, https://github.com/sivakumar-mahalingam/fastmrz/issues
Keywords: fastmrz,mrz,image processing,image recognition,ocr,computer vision,text recognition,text detection,artificial intelligence,onnx
Classifier: Intended Audience :: Developers
Classifier: License :: OSI Approved :: GNU Affero General Public License v3
Classifier: License :: OSI Approved :: GNU Affero General Public License v3 or later (AGPLv3+)
Classifier: Programming Language :: Python :: 3.8
Classifier: Programming Language :: Python :: 3.9
Classifier: Programming Language :: Python :: 3.10
Classifier: Programming Language :: Python :: 3.11
Classifier: Programming Language :: Python :: 3.12
Classifier: Operating System :: MacOS
Classifier: Operating System :: POSIX :: Linux
Classifier: Operating System :: Microsoft :: Windows :: Windows 10
Classifier: Operating System :: Microsoft :: Windows :: Windows 11
Classifier: Topic :: Scientific/Engineering
Classifier: Topic :: Scientific/Engineering :: Artificial Intelligence
Classifier: Topic :: Scientific/Engineering :: Image Processing
Classifier: Topic :: Scientific/Engineering :: Image Recognition
Classifier: Topic :: Scientific/Engineering :: Information Analysis
Classifier: Topic :: Software Development
Requires-Python: >=3.8
License-File: LICENSE
Requires-Dist: opencv-python >=4.9.0.80
Requires-Dist: pytesseract >=0.3.10
